Metadata-Version: 2.1
Name: python-testing-crawler
Version: 0.2.2
Summary: Python Test Crawler
Home-page: UNKNOWN
Author: Chris Wood
License: UNKNOWN
Keywords: python testing crawler
Platform: UNKNOWN
Classifier: Development Status :: 4 - Beta
Classifier: Intended Audience :: Developers
Classifier: License :: OSI Approved :: Mozilla Public License 2.0 (MPL 2.0)
Classifier: Operating System :: Unix
Classifier: Operating System :: POSIX
Classifier: Operating System :: Microsoft :: Windows
Classifier: Programming Language :: Python
Classifier: Programming Language :: Python :: 3
Classifier: Topic :: Software Development :: Testing
Requires-Python: >=3.6
Requires-Dist: bs4
Requires-Dist: soupsieve
Requires-Dist: dataclasses ; python_version < "3.7"
